CHANGES.txt
MANIFEST.in
README.txt
bootstrap.py
buildout.cfg
setup.py
docs/CHANGES.txt
docs/CREDITS.txt
docs/README.txt
src/hurry/__init__.py
src/hurry.datalink.egg-info/PKG-INFO
src/hurry.datalink.egg-info/SOURCES.txt
src/hurry.datalink.egg-info/dependency_links.txt
src/hurry.datalink.egg-info/entry_points.txt
src/hurry.datalink.egg-info/namespace_packages.txt
src/hurry.datalink.egg-info/not-zip-safe
src/hurry.datalink.egg-info/requires.txt
src/hurry.datalink.egg-info/top_level.txt
src/hurry/datalink/__init__.py
src/hurry/datalink/datalink.txt
src/hurry/datalink/tests.py
src/hurry/datalink/datalink-build/jquery.datalink.js