Metadata-Version: 1.0
Name: hurry.datalink
Version: 0.1
Summary: hurry.resource for JQuery Datalink
Home-page: UNKNOWN
Author: Martijn Faassen / Izhar Firdaus
Author-email: faassen@startifact.com
License: MIT
Platform: UNKNOWN
Classifier: Programming Language :: Python
Classifier: Topic :: Software Development :: Libraries :: Python Modules
